{
    "task": "FourQubitH2_QMLStateBasicGates",
    "pool": {
        "0": {
            "Rot": [
                0
            ]
        },
        "1": {
            "PlaceHolder": [
                0
            ]
        },
        "2": {
            "Rot": [
                1
            ]
        },
        "3": {
            "PlaceHolder": [
                1
            ]
        },
        "4": {
            "Rot": [
                2
            ]
        },
        "5": {
            "PlaceHolder": [
                2
            ]
        },
        "6": {
            "Rot": [
                3
            ]
        },
        "7": {
            "PlaceHolder": [
                3
            ]
        },
        "8": {
            "CNOT": [
                0,
                1
            ]
        },
        "9": {
            "CNOT": [
                1,
                0
            ]
        },
        "10": {
            "CNOT": [
                1,
                2
            ]
        },
        "11": {
            "CNOT": [
                2,
                1
            ]
        },
        "12": {
            "CNOT": [
                2,
                3
            ]
        },
        "13": {
            "CNOT": [
                3,
                2
            ]
        }
    },
    "params": [
        [
            [
                -2.21371587273931,
                -0.06852421521604692,
                0.35078124508637865
            ],
            [
                -2.934238700519623,
                0.40775022301593244,
                -0.4721318767839868
            ],
            [
                -0.2455872799132995,
                1.3711973325229936,
                0.038571533224465875
            ],
            [
                0.5846575807543225,
                1.6859107394142967,
                -0.3323963292827141
            ],
            [
                1.7561047600970345,
                -1.5467417022114944,
                0.7366062562087462
            ],
            [
                0.12692394679855937,
                0.36772609102899684,
                0.49642841964835943
            ],
            [
                0.490997551217511,
                -6.541529786882637e-10,
                1.064992966695962
            ],
            [
                -0.1356380598280805,
                -0.3702298777048839,
                -0.4365658084655793
            ],
            [
                -0.5406487536500784,
                0.8306468809445002,
                -0.1284165057454989
            ],
            [
                -0.35968324811533203,
                -0.26152329958127923,
                -0.1675356641180369
            ],
            [
                1.3053786465628932,
                -0.07676932966566644,
                -1.158342274091696
            ],
            [
                -0.8657441626307856,
                0.8528010985385884,
                0.44880086303506267
            ],
            [
                -1.0657428857530697,
                1.8030101221771857,
                -0.8788064013559866
            ],
            [
                0.7401800444449534,
                0.49185393775048847,
                1.7395045244701568
            ]
        ],
        [
            [
                0.2675193692853083,
                1.582908760884532e-10,
                -0.3986769289306143
            ],
            [
                1.679189064258657,
                0.8753180763625787,
                0.7317931810064319
            ],
            [
                1.2399052626200178,
                1.9249156124081912,
                -0.28884379484050365
            ],
            [
                1.0914377271976632,
                -0.17352501311246032,
                0.41695234174913115
            ],
            [
                1.4157914166746628,
                1.373692572496684,
                -0.0339375818691681
            ],
            [
                0.6064472124644605,
                -0.2793642662724722,
                -1.913790696704439
            ],
            [
                -0.573903833186578,
                0.11862152076140543,
                -0.05062108095308184
            ],
            [
                -0.5029679055250872,
                -1.2972167370735106,
                1.3823204800035502
            ],
            [
                -1.4709256768586705,
                -1.475560088191022,
                0.1369031313174433
            ],
            [
                0.9530803389757025,
                0.9441624769806681,
                0.6185521689229512
            ],
            [
                1.9354369383578331,
                -0.28836067091392453,
                -1.0686864741308018
            ],
            [
                0.10129792280885119,
                -1.3854776665570594,
                -2.4204019913883887
            ],
            [
                -0.1409090337573438,
                -0.7143399880113999,
                1.106378290398656
            ],
            [
                -1.0425717119015037,
                0.9694796399681693,
                -0.8382336409807652
            ]
        ],
        [
            [
                -0.09123950823740565,
                0.15095208943757704,
                -1.6853860186631302
            ],
            [
                -0.5546488621557197,
                -0.3306289751053423,
                0.4283011306173438
            ],
            [
                -0.11396807035700542,
                0.37660692323465855,
                1.4253988161927926
            ],
            [
                2.262171300182986,
                0.369550650974584,
                -0.6605230205147563
            ],
            [
                -0.5261798869413363,
                0.5769309759613581,
                -0.9087056337170458
            ],
            [
                -1.946908684258701,
                0.34103015504717965,
                1.2384395227562364
            ],
            [
                -0.9661451600132214,
                -0.05992863979065541,
                -0.19407215119142907
            ],
            [
                -2.433216667420971,
                0.8473961936435895,
                -0.21804023309334403
            ],
            [
                0.9005995495725615,
                -1.0849355782318,
                -1.1212879730047434
            ],
            [
                -0.9292100288917987,
                -1.4142328652240506,
                -0.5055954855468068
            ],
            [
                0.19960441453582203,
                -1.39020009595259,
                0.09554316182534907
            ],
            [
                -0.5197317641592961,
                -0.3257009422038148,
                0.29493860178605474
            ],
            [
                -0.53534809101503,
                -0.831121066271337,
                1.3683685332016877
            ],
            [
                2.4131004412195143,
                0.4965535811721945,
                -0.6612168502911805
            ]
        ],
        [
            [
                -0.18103273384127816,
                -0.47380318415584466,
                1.3856966211417139
            ],
            [
                -1.5502357588468232,
                -0.08350358776460137,
                1.2338512057556175
            ],
            [
                1.0215806504614575,
                -1.2408883220352274,
                -0.9113647137671116
            ],
            [
                1.5696934570045709,
                -0.6146978398329008,
                -0.5334065612286374
            ],
            [
                0.18164027341750544,
                1.257970915467318,
                -1.2121464472700787
            ],
            [
                0.5695925363868006,
                -0.3406228158304324,
                -0.18913252800829225
            ],
            [
                1.5076828257279473,
                1.0075974159835364,
                0.024379967184904105
            ],
            [
                0.013707905513540626,
                1.4427682891293807,
                -1.1432043026884242
            ],
            [
                -0.053116903826783204,
                -0.3849743678859767,
                0.11056425935222143
            ],
            [
                0.2705793178451235,
                -0.09476691788486709,
                0.8962078478172378
            ],
            [
                -1.162619955798693,
                0.6629678198642498,
                0.5720934869900411
            ],
            [
                -1.1633757919826744,
                1.3014301310679879,
                -0.5973913866806827
            ],
            [
                -0.25053722637260345,
                1.5382144753998348,
                0.19816750105560166
            ],
            [
                -0.8301285142088374,
                0.40889403864539586,
                -0.5613569752923365
            ]
        ],
        [
            [
                -0.26447675913139057,
                0.37136961182948963,
                -0.5834433406821649
            ],
            [
                0.6003903577874669,
                -1.361761837971829,
                0.4337305036172544
            ],
            [
                0.5842997800516774,
                0.5435734093398286,
                -1.1500635623180246
            ],
            [
                -0.768925667749742,
                1.194258038952645,
                0.3565849021845893
            ],
            [
                -0.9685291831819618,
                0.4805776651659883,
                -0.5471109282856662
            ],
            [
                1.0974167187159327,
                -0.3034799288961791,
                0.22849633970228023
            ],
            [
                0.5277345709790805,
                -0.16836260502911993,
                0.30301447713459
            ],
            [
                -0.7989909087719972,
                -0.8836100024659338,
                -0.831676241845107
            ],
            [
                -0.1690851891432026,
                0.4450250651398924,
                -0.38568316835421707
            ],
            [
                0.4687576085429595,
                -0.5054229209245725,
                -0.5027731935425729
            ],
            [
                -1.3111297872672718,
                -0.09783033117963506,
                0.579887414597463
            ],
            [
                -0.727615261699424,
                -0.8175919426870933,
                0.5103778653626672
            ],
            [
                -1.1632406407693694,
                -1.431655431835174,
                1.380712602128479
            ],
            [
                -2.480042644084846,
                0.9902891299985717,
                0.9280082331140034
            ]
        ],
        [
            [
                0.3447968393738723,
                -0.5835389088623311,
                1.5531774669902687
            ],
            [
                -0.6805483370763585,
                0.8976842629443245,
                -1.50066753651087
            ],
            [
                -0.18811519860098336,
                -0.6542828121834605,
                -0.002357348570137332
            ],
            [
                0.07097900085390291,
                -0.8243769477872745,
                0.6010649347091325
            ],
            [
                0.8067398563108487,
                -0.5345377744251222,
                -0.9123564406273607
            ],
            [
                0.6834701372801714,
                -1.405011391351131,
                -1.341629877331654
            ],
            [
                -0.13462095753503722,
                5.705826559074596e-11,
                -1.203291324007739
            ],
            [
                1.6379460857549188,
                -0.498231330056292,
                -0.41346468604147546
            ],
            [
                -0.7900175505213834,
                0.9847778828266309,
                -1.0751049550923608
            ],
            [
                0.5258032750553793,
                0.7636020474951096,
                1.5977081260645425
            ],
            [
                -1.4286209943245423,
                1.9554943862538297,
                0.4142988400061129
            ],
            [
                0.47591477428050866,
                -0.818973770853078,
                1.7018489662351302
            ],
            [
                -0.030279704794422324,
                0.03149434743917628,
                -2.047813412535846
            ],
            [
                0.1118286641776683,
                -2.5089297633299505,
                -0.05197673567503793
            ]
        ],
        [
            [
                -0.4858001098226698,
                0.29220196705863044,
                0.07700949377803436
            ],
            [
                0.32815759111592474,
                0.38510814447430397,
                0.29665313115552805
            ],
            [
                0.15256208352132178,
                -0.6055512876568012,
                -1.0078231020151782
            ],
            [
                -1.0305506622922358,
                -1.7381042107593325,
                0.7758926649972031
            ],
            [
                0.3105748112658784,
                -0.5274439153874023,
                -1.4644191111405775
            ],
            [
                -0.6027206287504491,
                1.443645106675835,
                -0.775945746335022
            ],
            [
                1.5832342075987187,
                1.604370811182228,
                -0.35749675487955607
            ],
            [
                -0.012446252889161128,
                -0.7397256413100922,
                0.5270385833774729
            ],
            [
                0.7125608510375163,
                1.393894689512057,
                1.6512683482013955
            ],
            [
                -0.9333467304299226,
                0.9321357189655737,
                0.9880733146630376
            ],
            [
                -2.6266599408886058,
                0.0663849385295922,
                -0.14854050123275903
            ],
            [
                1.9203288312097624,
                0.11288510338717148,
                -0.7966704205632834
            ],
            [
                0.14283302023790218,
                -0.8358998381338134,
                -0.0557638029102614
            ],
            [
                0.48236319756206236,
                0.6465630905745378,
                -0.025307842901084395
            ]
        ],
        [
            [
                -0.3112222155662309,
                0.7648473001075432,
                -1.9102203237496356
            ],
            [
                -0.4089572960230706,
                -1.3879938417664675,
                -3.178405315342659
            ],
            [
                0.3385102510989762,
                -0.19928773976657085,
                1.2950942320869674
            ],
            [
                -1.6424514749844779,
                -0.3924605889697752,
                -1.473470970266292
            ],
            [
                0.3706093703221621,
                0.08249843365922553,
                0.14529505902999382
            ],
            [
                -0.5140736365849412,
                -0.18202639184119548,
                0.28149899187101785
            ],
            [
                -0.4598502876463524,
                1.4273073631996476,
                1.1500919196975503
            ],
            [
                0.6687106546065046,
                0.7179167274792055,
                -0.49086165000225346
            ],
            [
                -0.40510457375617637,
                0.12873505702178592,
                -0.6793860609953825
            ],
            [
                -1.2203796413570858,
                -0.025720509276255542,
                -0.39903594095576894
            ],
            [
                2.5001158629019113,
                0.8983187495567476,
                -0.09452547091515594
            ],
            [
                0.5014008393492076,
                0.16949669363256697,
                -1.6469218304308773
            ],
            [
                -0.23787723031465313,
                -0.23121248988906126,
                -1.124066172823264
            ],
            [
                -1.2947219658875229,
                -0.06782652155339551,
                -0.5215819204496348
            ]
        ],
        [
            [
                -0.7097166527636436,
                0.026813515432155464,
                -0.8303409698205657
            ],
            [
                -0.029337352817907687,
                0.175106552109051,
                -1.545145549208704
            ],
            [
                1.318956824348287,
                0.43367674323366495,
                -1.6664530345646107
            ],
            [
                -0.7977465660236773,
                -0.1509645914436363,
                -1.1851026887608656
            ],
            [
                -0.9462683492099967,
                0.8610790607792199,
                1.563434770343573
            ],
            [
                1.781336789621093,
                0.06697815948144693,
                0.6987210996689568
            ],
            [
                -0.8933291600692578,
                -0.7548494217687428,
                -0.046697096087698994
            ],
            [
                -0.934631548355165,
                -0.7302189478890074,
                2.621555175461002
            ],
            [
                0.919614979538862,
                -1.065639928778852,
                -0.3392666885039867
            ],
            [
                -1.5804027719089184,
                -0.43960150414391647,
                0.4064511377396277
            ],
            [
                -0.4549538300621201,
                -0.516680260825715,
                -2.1346588924312186
            ],
            [
                2.018078478764777,
                0.4546015764189357,
                -0.024528443746342526
            ],
            [
                -1.7446234974355623,
                -0.06665553732704545,
                -2.1495464228565044
            ],
            [
                0.9649872380620371,
                -0.47029726522908744,
                -0.4148517581969664
            ]
        ],
        [
            [
                0.8617604343302956,
                0.11235749686276698,
                0.03589927507014389
            ],
            [
                1.1664458633357635,
                -1.7878778162688151,
                1.366305216747297
            ],
            [
                0.5442535319414139,
                -1.5765913997259646,
                -0.15910253746488112
            ],
            [
                -0.02107235508553884,
                0.8479875029914175,
                -1.4200424594977157
            ],
            [
                0.6347097047308998,
                1.0644761614671703,
                0.17354176283628353
            ],
            [
                0.9143942065687918,
                -0.3232291796426052,
                1.4235117365762502
            ],
            [
                -0.31765661017850794,
                0.5096461582607258,
                -0.7616320846062679
            ],
            [
                -0.7768341117599881,
                0.49567123973498256,
                0.31494938049558496
            ],
            [
                -0.27903993057330106,
                0.5460916920467022,
                -0.37142369558876565
            ],
            [
                -0.27943838828035267,
                -0.6892315829668405,
                -0.6949279717562533
            ],
            [
                -0.49252381543787327,
                0.6591570917430799,
                -0.7650633516000549
            ],
            [
                0.6015528466599398,
                0.15206069070556974,
                0.5314303554540475
            ],
            [
                0.06791505008236186,
                0.8517770658487317,
                0.5931903625900175
            ],
            [
                -2.12278930320345,
                0.6952588937409083,
                0.7120461586366339
            ]
        ]
    ],
    "k": [
        6,
        0,
        13,
        1,
        5,
        6,
        12,
        7,
        13,
        12
    ],
    "op_list": [
        [
            "Rot",
            [
                3
            ],
            [
                0.490997551217511,
                -6.541529786882637e-10,
                1.064992966695962
            ]
        ],
        [
            "Rot",
            [
                0
            ],
            [
                0.2675193692853083,
                1.582908760884532e-10,
                -0.3986769289306143
            ]
        ],
        [
            "CNOT",
            [
                3,
                2
            ],
            null
        ],
        [
            "Rot",
            [
                3
            ],
            [
                -0.13462095753503722,
                5.705826559074596e-11,
                -1.203291324007739
            ]
        ],
        [
            "CNOT",
            [
                2,
                3
            ],
            null
        ],
        [
            "CNOT",
            [
                3,
                2
            ],
            null
        ],
        [
            "CNOT",
            [
                2,
                3
            ],
            null
        ]
    ],
    "search_reward_list": [
        [
            0,
            [
                6,
                4,
                5,
                5,
                7,
                5,
                5,
                7,
                7,
                11
            ],
            1.0720247721952438,
            1.0720247721952438
        ],
        [
            1,
            [
                0,
                4,
                1,
                6,
                1,
                1,
                1,
                1,
                7,
                5
            ],
            0.9008583015351587,
            0.9008583015351587
        ],
        [
            2,
            [
                0,
                8,
                10,
                8,
                11,
                0,
                6,
                5,
                5,
                3
            ],
            0.7870745884189758,
            0.7870745884189758
        ],
        [
            3,
            [
                4,
                2,
                10,
                4,
                3,
                12,
                6,
                12,
                4,
                13
            ],
            0.8172800196402019,
            0.8172800196402019
        ],
        [
            4,
            [
                0,
                4,
                12,
                4,
                6,
                12,
                5,
                1,
                7,
                4
            ],
            0.8941381865034368,
            0.8941381865034368
        ],
        [
            5,
            [
                4,
                0,
                2,
                9,
                12,
                13,
                2,
                6,
                8,
                1
            ],
            0.7881875302051735,
            0.7881875302051735
        ],
        [
            6,
            [
                0,
                1,
                4,
                12,
                13,
                6,
                8,
                11,
                2,
                12
            ],
            1.0079618852408927,
            1.0079618852408927
        ],
        [
            7,
            [
                2,
                4,
                5,
                11,
                9,
                4,
                8,
                1,
                5,
                3
            ],
            1.0185605981658648,
            1.0185605981658648
        ],
        [
            8,
            [
                0,
                8,
                10,
                2,
                11,
                1,
                12,
                7,
                13,
                2
            ],
            0.763687387531738,
            0.763687387531738
        ],
        [
            9,
            [
                2,
                10,
                12,
                10,
                6,
                7,
                5,
                11,
                12,
                6
            ],
            0.9939769445855715,
            0.9939769445855715
        ],
        [
            10,
            [
                0,
                6,
                8,
                7,
                9,
                2,
                8,
                3,
                7,
                1
            ],
            0.8610788775025021,
            0.8610788775025021
        ],
        [
            11,
            [
                4,
                0,
                1,
                11,
                4,
                9,
                10,
                8,
                3,
                4
            ],
            1.0042051122010476,
            1.0042051122010476
        ],
        [
            12,
            [
                4,
                0,
                6,
                13,
                4,
                1,
                7,
                5,
                13,
                11
            ],
            0.8493890098442829,
            0.8493890098442829
        ],
        [
            13,
            [
                0,
                6,
                7,
                4,
                1,
                5,
                5,
                5,
                13,
                11
            ],
            1.0211693916438676,
            1.0211693916438676
        ],
        [
            14,
            [
                2,
                6,
                3,
                3,
                3,
                7,
                4,
                5,
                3,
                11
            ],
            0.9109190825618936,
            0.9109190825618936
        ],
        [
            15,
            [
                0,
                8,
                10,
                8,
                0,
                8,
                9,
                3,
                12,
                13
            ],
            1.002469566929295,
            1.002469566929295
        ],
        [
            16,
            [
                0,
                1,
                6,
                4,
                5,
                5,
                13,
                5,
                12,
                13
            ],
            1.0570228428513337,
            1.0570228428513337
        ],
        [
            17,
            [
                6,
                0,
                1,
                8,
                3,
                0,
                8,
                3,
                1,
                1
            ],
            0.9022767633891906,
            0.9022767633891906
        ],
        [
            18,
            [
                0,
                1,
                6,
                7,
                13,
                7,
                4,
                1,
                7,
                11
            ],
            1.0553315648162673,
            1.0553315648162673
        ],
        [
            19,
            [
                6,
                13,
                5,
                6,
                12,
                7,
                7,
                5,
                7,
                11
            ],
            1.0719674004020838,
            1.0719674004020838
        ],
        [
            20,
            [
                6,
                7,
                4,
                13,
                7,
                6,
                4,
                7,
                5,
                11
            ],
            0.9854704929080986,
            0.9854704929080986
        ],
        [
            21,
            [
                6,
                13,
                5,
                7,
                7,
                4,
                13,
                7,
                7,
                11
            ],
            1.0883507837360957,
            1.0883507837360957
        ],
        [
            22,
            [
                2,
                0,
                1,
                6,
                13,
                8,
                1,
                5,
                5,
                12
            ],
            1.062907838407682,
            1.062907838407682
        ],
        [
            23,
            [
                6,
                13,
                5,
                4,
                0,
                12,
                1,
                5,
                7,
                11
            ],
            1.06884673370997,
            1.06884673370997
        ],
        [
            24,
            [
                6,
                0,
                13,
                6,
                4,
                12,
                7,
                13,
                5,
                11
            ],
            0.9470362460959297,
            0.9470362460959297
        ],
        [
            25,
            [
                6,
                13,
                6,
                4,
                5,
                5,
                5,
                7,
                7,
                12
            ],
            1.0621108454390007,
            1.0621108454390007
        ],
        [
            26,
            [
                6,
                0,
                7,
                4,
                5,
                7,
                1,
                1,
                7,
                11
            ],
            1.0792069741045378,
            1.0792069741045378
        ],
        [
            27,
            [
                6,
                13,
                0,
                5,
                7,
                5,
                4,
                1,
                1,
                11
            ],
            1.0896010636306606,
            1.0896010636306606
        ],
        [
            28,
            [
                6,
                7,
                0,
                4,
                12,
                6,
                5,
                7,
                12,
                11
            ],
            1.050755351437612,
            1.050755351437612
        ],
        [
            29,
            [
                6,
                13,
                12,
                0,
                13,
                4,
                13,
                5,
                7,
                11
            ],
            1.0620804727373159,
            1.0620804727373159
        ],
        [
            30,
            [
                6,
                0,
                13,
                6,
                7,
                1,
                1,
                7,
                12,
                11
            ],
            1.0889669955465981,
            1.0889669955465981
        ],
        [
            31,
            [
                6,
                13,
                12,
                7,
                5,
                13,
                12,
                4,
                5,
                13
            ],
            1.082916084170416,
            1.082916084170416
        ],
        [
            32,
            [
                6,
                4,
                7,
                7,
                7,
                0,
                7,
                7,
                5,
                1
            ],
            1.0734639531337096,
            1.0734639531337096
        ],
        [
            33,
            [
                6,
                7,
                13,
                12,
                6,
                5,
                7,
                5,
                0,
                11
            ],
            1.1078824758069614,
            1.1078824758069614
        ],
        [
            34,
            [
                6,
                0,
                7,
                13,
                12,
                5,
                4,
                5,
                5,
                11
            ],
            1.0998279188588131,
            1.0998279188588131
        ],
        [
            35,
            [
                0,
                1,
                4,
                5,
                6,
                7,
                5,
                5,
                1,
                11
            ],
            1.0965763670941462,
            1.0965763670941462
        ],
        [
            36,
            [
                6,
                7,
                7,
                13,
                5,
                7,
                12,
                13,
                7,
                11
            ],
            1.09665160764089,
            1.09665160764089
        ],
        [
            37,
            [
                6,
                2,
                9,
                10,
                5,
                8,
                1,
                1,
                5,
                1
            ],
            1.0863907720455828,
            1.0863907720455828
        ],
        [
            38,
            [
                6,
                13,
                7,
                12,
                5,
                6,
                5,
                13,
                12,
                13
            ],
            1.058280029564738,
            1.058280029564738
        ],
        [
            39,
            [
                0,
                6,
                13,
                5,
                5,
                4,
                12,
                1,
                13,
                11
            ],
            1.04653060521938,
            1.04653060521938
        ],
        [
            40,
            [
                6,
                0,
                8,
                2,
                10,
                4,
                8,
                12,
                6,
                12
            ],
            1.044329066131523,
            1.044329066131523
        ],
        [
            41,
            [
                2,
                0,
                4,
                5,
                6,
                1,
                10,
                2,
                3,
                7
            ],
            1.0416165743345172,
            1.0416165743345172
        ],
        [
            42,
            [
                0,
                8,
                4,
                9,
                1,
                5,
                6,
                8,
                5,
                11
            ],
            1.104464773712284,
            1.104464773712284
        ],
        [
            43,
            [
                6,
                13,
                4,
                6,
                12,
                0,
                13,
                1,
                5,
                11
            ],
            1.0946335749267393,
            1.0946335749267393
        ],
        [
            44,
            [
                0,
                8,
                2,
                1,
                3,
                3,
                4,
                8,
                2,
                11
            ],
            1.1050603357961717,
            1.1050603357961717
        ],
        [
            45,
            [
                6,
                13,
                5,
                6,
                12,
                7,
                5,
                13,
                2,
                11
            ],
            1.1048861656489881,
            1.1048861656489881
        ],
        [
            46,
            [
                6,
                0,
                7,
                1,
                13,
                7,
                7,
                6,
                7,
                12
            ],
            1.0892733983887668,
            1.0892733983887668
        ],
        [
            47,
            [
                6,
                0,
                4,
                1,
                12,
                4,
                1,
                13,
                1,
                11
            ],
            1.0996359370182658,
            1.0996359370182658
        ],
        [
            48,
            [
                6,
                13,
                0,
                7,
                12,
                7,
                13,
                5,
                1,
                11
            ],
            1.1148234880294796,
            1.1148234880294796
        ],
        [
            49,
            [
                6,
                4,
                12,
                6,
                5,
                13,
                6,
                5,
                7,
                12
            ],
            1.1149926820044478,
            1.1149926820044478
        ],
        [
            50,
            [
                6,
                2,
                10,
                0,
                12,
                1,
                13,
                2,
                11,
                12
            ],
            1.0611786697277246,
            1.0611786697277246
        ],
        [
            51,
            [
                2,
                3,
                4,
                5,
                5,
                9,
                5,
                8,
                3,
                11
            ],
            1.0624873495777711,
            1.0624873495777711
        ],
        [
            52,
            [
                6,
                7,
                0,
                13,
                12,
                8,
                9,
                2,
                11,
                7
            ],
            1.1033289662514894,
            1.1033289662514894
        ],
        [
            53,
            [
                6,
                4,
                12,
                13,
                11,
                7,
                4,
                5,
                2,
                13
            ],
            1.0105484198598458,
            1.0105484198598458
        ],
        [
            54,
            [
                2,
                4,
                6,
                7,
                11,
                2,
                10,
                2,
                5,
                3
            ],
            1.057467592625676,
            1.057467592625676
        ],
        [
            55,
            [
                6,
                0,
                4,
                1,
                13,
                12,
                4,
                5,
                6,
                11
            ],
            1.0497450644155555,
            1.0497450644155555
        ],
        [
            56,
            [
                0,
                6,
                1,
                1,
                13,
                1,
                5,
                4,
                6,
                12
            ],
            1.0910432326917119,
            1.0910432326917119
        ],
        [
            57,
            [
                6,
                13,
                6,
                7,
                4,
                13,
                5,
                5,
                6,
                11
            ],
            1.113054855040746,
            1.113054855040746
        ],
        [
            58,
            [
                6,
                13,
                5,
                5,
                7,
                7,
                12,
                7,
                4,
                11
            ],
            1.0888894454030171,
            1.0888894454030171
        ],
        [
            59,
            [
                2,
                3,
                4,
                9,
                2,
                9,
                1,
                2,
                8,
                11
            ],
            0.9831850807638082,
            0.9831850807638082
        ],
        [
            60,
            [
                0,
                8,
                3,
                0,
                6,
                1,
                10,
                8,
                5,
                11
            ],
            1.0937988007377815,
            1.0937988007377815
        ],
        [
            61,
            [
                2,
                3,
                4,
                0,
                1,
                10,
                8,
                1,
                6,
                11
            ],
            1.1020500359725582,
            1.1020500359725582
        ],
        [
            62,
            [
                6,
                7,
                7,
                7,
                4,
                5,
                13,
                12,
                6,
                11
            ],
            1.077129029213349,
            1.077129029213349
        ],
        [
            63,
            [
                2,
                10,
                2,
                0,
                4,
                5,
                3,
                8,
                3,
                11
            ],
            1.0988702904136765,
            1.0988702904136765
        ],
        [
            64,
            [
                2,
                3,
                10,
                9,
                4,
                2,
                10,
                8,
                4,
                11
            ],
            1.079544947508802,
            1.079544947508802
        ],
        [
            65,
            [
                6,
                13,
                12,
                7,
                5,
                4,
                7,
                12,
                4,
                11
            ],
            1.0891251801525135,
            1.0891251801525135
        ],
        [
            66,
            [
                2,
                9,
                10,
                1,
                1,
                8,
                5,
                6,
                4,
                1
            ],
            1.0639485836106575,
            1.0639485836106575
        ],
        [
            67,
            [
                4,
                12,
                13,
                5,
                7,
                4,
                5,
                0,
                7,
                11
            ],
            1.112328709336705,
            1.112328709336705
        ],
        [
            68,
            [
                2,
                3,
                4,
                9,
                5,
                11,
                1,
                3,
                8,
                3
            ],
            1.1146791318402718,
            1.1146791318402718
        ],
        [
            69,
            [
                2,
                6,
                4,
                7,
                9,
                3,
                8,
                3,
                12,
                11
            ],
            1.1113625029363305,
            1.1113625029363305
        ],
        [
            70,
            [
                2,
                4,
                9,
                6,
                13,
                8,
                3,
                2,
                6,
                11
            ],
            1.0758838671445166,
            1.0758838671445166
        ],
        [
            71,
            [
                0,
                8,
                6,
                13,
                7,
                3,
                9,
                8,
                6,
                12
            ],
            1.0978904452516949,
            1.0978904452516949
        ],
        [
            72,
            [
                6,
                7,
                13,
                6,
                5,
                7,
                5,
                12,
                4,
                11
            ],
            1.075392881358533,
            1.075392881358533
        ],
        [
            73,
            [
                6,
                0,
                13,
                1,
                5,
                12,
                5,
                6,
                1,
                11
            ],
            1.0886663546712034,
            1.0886663546712034
        ],
        [
            74,
            [
                2,
                6,
                3,
                0,
                3,
                8,
                4,
                7,
                5,
                11
            ],
            1.1026625428099575,
            1.1026625428099575
        ],
        [
            75,
            [
                6,
                7,
                13,
                6,
                7,
                5,
                5,
                5,
                12,
                6
            ],
            1.0904110568250576,
            1.0904110568250576
        ],
        [
            76,
            [
                2,
                6,
                3,
                4,
                11,
                9,
                12,
                8,
                7,
                13
            ],
            1.0891703330102223,
            1.0891703330102223
        ],
        [
            77,
            [
                6,
                4,
                12,
                7,
                13,
                12,
                13,
                12,
                7,
                11
            ],
            1.080315669973188,
            1.080315669973188
        ],
        [
            78,
            [
                2,
                4,
                5,
                0,
                11,
                4,
                8,
                3,
                3,
                5
            ],
            1.0090272251061303,
            1.0090272251061303
        ],
        [
            79,
            [
                0,
                8,
                10,
                9,
                1,
                1,
                5,
                8,
                6,
                1
            ],
            1.1157174209853085,
            1.1157174209853085
        ],
        [
            80,
            [
                6,
                7,
                4,
                12,
                4,
                5,
                7,
                2,
                7,
                11
            ],
            1.0532584355935914,
            1.0532584355935914
        ],
        [
            81,
            [
                4,
                6,
                12,
                5,
                13,
                6,
                12,
                6,
                5,
                11
            ],
            1.1036030635823264,
            1.1036030635823264
        ],
        [
            82,
            [
                2,
                10,
                12,
                9,
                10,
                1,
                8,
                3,
                4,
                11
            ],
            1.107976547848515,
            1.107976547848515
        ],
        [
            83,
            [
                2,
                6,
                0,
                10,
                5,
                3,
                4,
                1,
                8,
                11
            ],
            1.0773848091719054,
            1.0773848091719054
        ],
        [
            84,
            [
                2,
                4,
                5,
                6,
                11,
                9,
                10,
                8,
                3,
                1
            ],
            1.09241241460129,
            1.09241241460129
        ],
        [
            85,
            [
                6,
                7,
                0,
                1,
                13,
                1,
                4,
                5,
                1,
                13
            ],
            1.0781567590306944,
            1.0781567590306944
        ],
        [
            86,
            [
                6,
                0,
                7,
                4,
                1,
                5,
                12,
                4,
                5,
                6
            ],
            1.073422070106536,
            1.073422070106536
        ],
        [
            87,
            [
                6,
                13,
                7,
                4,
                5,
                6,
                7,
                12,
                4,
                11
            ],
            1.0522631191517735,
            1.0522631191517735
        ],
        [
            88,
            [
                6,
                7,
                7,
                0,
                13,
                12,
                1,
                7,
                4,
                11
            ],
            1.0784398069730106,
            1.0784398069730106
        ],
        [
            89,
            [
                6,
                13,
                12,
                4,
                12,
                6,
                7,
                12,
                4,
                11
            ],
            1.0301302066694298,
            1.0301302066694298
        ],
        [
            90,
            [
                2,
                3,
                6,
                0,
                3,
                3,
                13,
                10,
                8,
                13
            ],
            0.992140129986623,
            0.992140129986623
        ],
        [
            91,
            [
                4,
                6,
                0,
                12,
                6,
                13,
                1,
                12,
                4,
                11
            ],
            1.0673681450108106,
            1.0673681450108106
        ],
        [
            92,
            [
                0,
                6,
                1,
                4,
                5,
                5,
                7,
                2,
                1,
                11
            ],
            1.0551213378533306,
            1.0551213378533306
        ],
        [
            93,
            [
                4,
                12,
                7,
                0,
                6,
                12,
                13,
                12,
                4,
                11
            ],
            1.083029816950056,
            1.083029816950056
        ],
        [
            94,
            [
                6,
                13,
                12,
                13,
                5,
                12,
                2,
                4,
                6,
                11
            ],
            1.0717331150677454,
            1.0717331150677454
        ],
        [
            95,
            [
                0,
                8,
                10,
                12,
                9,
                6,
                7,
                8,
                5,
                12
            ],
            1.1136140216407222,
            1.1136140216407222
        ],
        [
            96,
            [
                0,
                4,
                5,
                12,
                5,
                6,
                1,
                7,
                4,
                11
            ],
            1.0850220744395882,
            1.0850220744395882
        ],
        [
            97,
            [
                2,
                3,
                3,
                3,
                3,
                10,
                12,
                13,
                2,
                5
            ],
            0.8402235190739945,
            0.8402235190739945
        ],
        [
            98,
            [
                2,
                6,
                0,
                10,
                3,
                3,
                9,
                8,
                5,
                1
            ],
            1.0469852280100695,
            1.0469852280100695
        ],
        [
            99,
            [
                0,
                1,
                6,
                13,
                5,
                6,
                5,
                4,
                12,
                11
            ],
            1.1100374613599722,
            1.1100374613599722
        ],
        [
            100,
            [
                2,
                0,
                3,
                10,
                6,
                5,
                2,
                1,
                4,
                1
            ],
            0.8985282239823779,
            0.8985282239823779
        ],
        [
            101,
            [
                2,
                6,
                3,
                9,
                2,
                4,
                10,
                8,
                4,
                5
            ],
            1.0827477693398424,
            1.0827477693398424
        ],
        [
            102,
            [
                2,
                6,
                0,
                1,
                3,
                7,
                9,
                8,
                4,
                11
            ],
            1.0862644169488525,
            1.0862644169488525
        ],
        [
            103,
            [
                2,
                6,
                10,
                0,
                3,
                11,
                2,
                3,
                4,
                11
            ],
            1.036510254991901,
            1.036510254991901
        ],
        [
            104,
            [
                6,
                4,
                13,
                6,
                13,
                6,
                7,
                12,
                4,
                11
            ],
            1.0609388384340377,
            1.0609388384340377
        ],
        [
            105,
            [
                2,
                4,
                9,
                1,
                3,
                1,
                10,
                8,
                4,
                11
            ],
            1.0911327696251523,
            1.0911327696251523
        ],
        [
            106,
            [
                6,
                0,
                4,
                7,
                12,
                1,
                13,
                7,
                12,
                11
            ],
            1.0737230722999351,
            1.0737230722999351
        ],
        [
            107,
            [
                2,
                3,
                4,
                0,
                6,
                8,
                0,
                11,
                4,
                11
            ],
            0.9832532260838024,
            0.9832532260838024
        ],
        [
            108,
            [
                0,
                1,
                1,
                4,
                8,
                9,
                8,
                6,
                5,
                11
            ],
            1.0579437994901448,
            1.0579437994901448
        ],
        [
            109,
            [
                6,
                13,
                0,
                12,
                1,
                6,
                7,
                7,
                1,
                11
            ],
            1.097719053580761,
            1.097719053580761
        ],
        [
            110,
            [
                6,
                0,
                13,
                5,
                1,
                12,
                5,
                7,
                7,
                11
            ],
            1.1038044454183262,
            1.1038044454183262
        ],
        [
            111,
            [
                6,
                7,
                0,
                7,
                1,
                4,
                7,
                12,
                1,
                11
            ],
            1.0744624156766387,
            1.0744624156766387
        ],
        [
            112,
            [
                4,
                6,
                0,
                11,
                3,
                12,
                2,
                8,
                3,
                11
            ],
            1.0760001256587925,
            1.0760001256587925
        ],
        [
            113,
            [
                4,
                12,
                5,
                4,
                7,
                5,
                5,
                5,
                7,
                11
            ],
            1.0672897628895988,
            1.0672897628895988
        ],
        [
            114,
            [
                0,
                6,
                7,
                13,
                12,
                6,
                1,
                5,
                7,
                4
            ],
            1.0703919757743285,
            1.0703919757743285
        ],
        [
            115,
            [
                4,
                5,
                12,
                13,
                5,
                4,
                5,
                13,
                4,
                11
            ],
            1.1080079574882211,
            1.1080079574882211
        ],
        [
            116,
            [
                0,
                1,
                6,
                1,
                13,
                7,
                5,
                5,
                4,
                13
            ],
            1.1142613260019674,
            1.1142613260019674
        ],
        [
            117,
            [
                6,
                7,
                0,
                7,
                13,
                1,
                6,
                12,
                4,
                6
            ],
            1.105398783623588,
            1.105398783623588
        ],
        [
            118,
            [
                6,
                7,
                7,
                7,
                13,
                12,
                7,
                5,
                4,
                11
            ],
            1.1109554817653153,
            1.1109554817653153
        ],
        [
            119,
            [
                6,
                0,
                1,
                7,
                13,
                12,
                7,
                7,
                4,
                11
            ],
            1.0932178361447822,
            1.0932178361447822
        ],
        [
            120,
            [
                0,
                6,
                7,
                1,
                1,
                13,
                6,
                4,
                12,
                11
            ],
            1.099700234994216,
            1.099700234994216
        ],
        [
            121,
            [
                0,
                1,
                1,
                6,
                4,
                13,
                4,
                5,
                1,
                13
            ],
            1.1161448580370763,
            1.1161448580370763
        ],
        [
            122,
            [
                6,
                13,
                7,
                4,
                12,
                5,
                7,
                13,
                4,
                11
            ],
            1.1011123123694844,
            1.1011123123694844
        ],
        [
            123,
            [
                6,
                7,
                13,
                12,
                13,
                12,
                13,
                7,
                7,
                7
            ],
            1.1154561068609903,
            1.1154561068609903
        ],
        [
            124,
            [
                0,
                2,
                1,
                3,
                1,
                4,
                8,
                2,
                3,
                11
            ],
            1.1122291176360968,
            1.1122291176360968
        ],
        [
            125,
            [
                6,
                4,
                7,
                0,
                1,
                5,
                1,
                13,
                12,
                11
            ],
            1.0915613756070879,
            1.0915613756070879
        ],
        [
            126,
            [
                0,
                4,
                5,
                6,
                5,
                1,
                1,
                1,
                13,
                11
            ],
            1.1112890149334254,
            1.1112890149334254
        ],
        [
            127,
            [
                6,
                4,
                13,
                6,
                5,
                7,
                7,
                7,
                4,
                12
            ],
            1.0934173849311168,
            1.0934173849311168
        ],
        [
            128,
            [
                6,
                4,
                13,
                12,
                0,
                11,
                5,
                12,
                13,
                12
            ],
            1.097443323009288,
            1.097443323009288
        ],
        [
            129,
            [
                4,
                2,
                0,
                3,
                11,
                1,
                6,
                8,
                7,
                5
            ],
            1.0564885561201502,
            1.0564885561201502
        ],
        [
            130,
            [
                6,
                4,
                0,
                7,
                12,
                13,
                7,
                6,
                1,
                12
            ],
            1.0936187368158627,
            1.0936187368158627
        ],
        [
            131,
            [
                6,
                13,
                0,
                6,
                4,
                7,
                12,
                5,
                6,
                11
            ],
            1.073188574151532,
            1.073188574151532
        ],
        [
            132,
            [
                6,
                4,
                0,
                5,
                7,
                5,
                5,
                1,
                5,
                11
            ],
            1.094000634521103,
            1.094000634521103
        ],
        [
            133,
            [
                0,
                1,
                6,
                1,
                4,
                7,
                7,
                13,
                4,
                11
            ],
            1.0409561970884458,
            1.0409561970884458
        ],
        [
            134,
            [
                0,
                8,
                1,
                4,
                0,
                3,
                8,
                5,
                3,
                11
            ],
            0.9789348190834025,
            0.9789348190834025
        ],
        [
            135,
            [
                4,
                12,
                5,
                4,
                7,
                12,
                6,
                5,
                4,
                11
            ],
            1.1103815948299178,
            1.1103815948299178
        ],
        [
            136,
            [
                0,
                6,
                4,
                7,
                1,
                5,
                5,
                5,
                5,
                11
            ],
            1.0747621815063353,
            1.0747621815063353
        ],
        [
            137,
            [
                6,
                7,
                4,
                5,
                7,
                5,
                7,
                7,
                7,
                11
            ],
            1.0458894193827617,
            1.0458894193827617
        ],
        [
            138,
            [
                6,
                7,
                13,
                5,
                12,
                6,
                5,
                5,
                7,
                11
            ],
            1.1154978410658913,
            1.1154978410658913
        ],
        [
            139,
            [
                0,
                4,
                12,
                13,
                1,
                12,
                5,
                5,
                6,
                7
            ],
            1.0784695975046625,
            1.0784695975046625
        ],
        [
            140,
            [
                6,
                7,
                7,
                7,
                13,
                5,
                4,
                11,
                6,
                13
            ],
            1.1002824020996007,
            1.1002824020996007
        ],
        [
            141,
            [
                4,
                5,
                0,
                2,
                3,
                5,
                1,
                8,
                5,
                2
            ],
            1.1050138138600964,
            1.1050138138600964
        ],
        [
            142,
            [
                6,
                7,
                4,
                13,
                4,
                5,
                5,
                7,
                13,
                11
            ],
            1.1119265302712484,
            1.1119265302712484
        ],
        [
            143,
            [
                0,
                4,
                6,
                2,
                8,
                1,
                7,
                1,
                5,
                5
            ],
            1.0647340693738994,
            1.0647340693738994
        ],
        [
            144,
            [
                6,
                4,
                0,
                5,
                7,
                12,
                4,
                1,
                5,
                12
            ],
            1.1068623641049962,
            1.1068623641049962
        ],
        [
            145,
            [
                6,
                7,
                7,
                4,
                13,
                12,
                4,
                6,
                5,
                13
            ],
            1.1074724884302605,
            1.1074724884302605
        ],
        [
            146,
            [
                0,
                6,
                2,
                3,
                10,
                11,
                8,
                7,
                4,
                11
            ],
            1.084788481127967,
            1.084788481127967
        ],
        [
            147,
            [
                6,
                7,
                13,
                12,
                5,
                7,
                7,
                7,
                6,
                11
            ],
            1.1035746196584346,
            1.1035746196584346
        ],
        [
            148,
            [
                6,
                0,
                4,
                7,
                7,
                2,
                3,
                3,
                5,
                11
            ],
            1.1038807362966838,
            1.1038807362966838
        ],
        [
            149,
            [
                2,
                4,
                11,
                6,
                9,
                5,
                8,
                3,
                5,
                5
            ],
            1.094034771807814,
            1.094034771807814
        ],
        [
            150,
            [
                6,
                7,
                4,
                0,
                12,
                5,
                5,
                6,
                7,
                12
            ],
            1.0982351511520454,
            1.0982351511520454
        ],
        [
            151,
            [
                6,
                0,
                4,
                2,
                5,
                5,
                8,
                1,
                1,
                11
            ],
            1.1000178560499272,
            1.1000178560499272
        ],
        [
            152,
            [
                6,
                13,
                0,
                1,
                1,
                5,
                1,
                5,
                6,
                12
            ],
            1.085121433036203,
            1.085121433036203
        ],
        [
            153,
            [
                2,
                6,
                3,
                7,
                0,
                13,
                10,
                8,
                3,
                13
            ],
            1.096237839824984,
            1.096237839824984
        ],
        [
            154,
            [
                6,
                4,
                13,
                4,
                0,
                6,
                7,
                5,
                5,
                11
            ],
            1.0398738180927622,
            1.0398738180927622
        ],
        [
            155,
            [
                6,
                13,
                5,
                12,
                7,
                13,
                12,
                5,
                6,
                12
            ],
            1.1153217028053999,
            1.1153217028053999
        ],
        [
            156,
            [
                6,
                7,
                0,
                4,
                13,
                6,
                4,
                13,
                6,
                11
            ],
            1.0987911376860706,
            1.0987911376860706
        ],
        [
            157,
            [
                6,
                13,
                4,
                7,
                12,
                5,
                4,
                5,
                6,
                13
            ],
            1.1022338936937865,
            1.1022338936937865
        ],
        [
            158,
            [
                6,
                4,
                0,
                12,
                7,
                5,
                4,
                13,
                4,
                11
            ],
            1.105375165127049,
            1.105375165127049
        ],
        [
            159,
            [
                6,
                7,
                4,
                7,
                13,
                4,
                0,
                13,
                4,
                11
            ],
            1.0784818636636138,
            1.0784818636636138
        ],
        [
            160,
            [
                6,
                7,
                7,
                7,
                0,
                13,
                1,
                12,
                4,
                11
            ],
            1.1170182231235464,
            1.1170182231235464
        ],
        [
            161,
            [
                6,
                0,
                13,
                7,
                4,
                1,
                5,
                13,
                4,
                11
            ],
            1.1118978375669029,
            1.1118978375669029
        ],
        [
            162,
            [
                6,
                7,
                4,
                5,
                7,
                13,
                0,
                12,
                4,
                13
            ],
            1.0531901011872713,
            1.0531901011872713
        ],
        [
            163,
            [
                6,
                7,
                13,
                4,
                7,
                7,
                7,
                7,
                5,
                11
            ],
            1.116435139234406,
            1.116435139234406
        ],
        [
            164,
            [
                0,
                6,
                4,
                13,
                1,
                4,
                1,
                13,
                6,
                4
            ],
            1.0657526593605606,
            1.0657526593605606
        ],
        [
            165,
            [
                6,
                13,
                4,
                6,
                7,
                13,
                6,
                7,
                7,
                12
            ],
            1.098907582857117,
            1.098907582857117
        ],
        [
            166,
            [
                4,
                12,
                0,
                1,
                6,
                5,
                4,
                1,
                5,
                11
            ],
            1.1017517732106403,
            1.1017517732106403
        ],
        [
            167,
            [
                6,
                0,
                8,
                9,
                2,
                8,
                13,
                6,
                12,
                11
            ],
            1.1083225635273746,
            1.1083225635273746
        ],
        [
            168,
            [
                4,
                0,
                6,
                12,
                13,
                4,
                12,
                6,
                12,
                11
            ],
            1.0617933595956632,
            1.0617933595956632
        ],
        [
            169,
            [
                6,
                0,
                4,
                7,
                5,
                1,
                13,
                6,
                7,
                11
            ],
            1.1122199745344228,
            1.1122199745344228
        ],
        [
            170,
            [
                6,
                0,
                1,
                4,
                5,
                1,
                5,
                13,
                6,
                11
            ],
            1.0915864304545608,
            1.0915864304545608
        ],
        [
            171,
            [
                6,
                0,
                1,
                1,
                4,
                13,
                4,
                12,
                13,
                11
            ],
            1.0935218824255455,
            1.0935218824255455
        ],
        [
            172,
            [
                6,
                7,
                0,
                1,
                7,
                4,
                1,
                5,
                1,
                7
            ],
            1.0772492436843695,
            1.0772492436843695
        ],
        [
            173,
            [
                6,
                0,
                2,
                4,
                3,
                8,
                13,
                3,
                11,
                13
            ],
            1.0806903349879455,
            1.0806903349879455
        ],
        [
            174,
            [
                0,
                6,
                4,
                1,
                5,
                1,
                1,
                13,
                4,
                11
            ],
            1.0983875581075309,
            1.0983875581075309
        ],
        [
            175,
            [
                6,
                0,
                4,
                5,
                13,
                4,
                1,
                1,
                13,
                4
            ],
            1.0892206779364932,
            1.0892206779364932
        ],
        [
            176,
            [
                6,
                13,
                7,
                5,
                4,
                13,
                4,
                6,
                7,
                11
            ],
            1.0699175427950505,
            1.0699175427950505
        ],
        [
            177,
            [
                0,
                4,
                12,
                4,
                2,
                6,
                5,
                5,
                7,
                11
            ],
            1.0411073083364244,
            1.0411073083364244
        ],
        [
            178,
            [
                6,
                0,
                1,
                1,
                7,
                13,
                12,
                13,
                12,
                13
            ],
            1.1133406825060324,
            1.1133406825060324
        ],
        [
            179,
            [
                0,
                6,
                7,
                4,
                7,
                7,
                7,
                1,
                1,
                11
            ],
            1.1144351401130836,
            1.1144351401130836
        ],
        [
            180,
            [
                6,
                7,
                13,
                0,
                7,
                7,
                7,
                4,
                13,
                6
            ],
            1.098626872054791,
            1.098626872054791
        ],
        [
            181,
            [
                6,
                0,
                13,
                12,
                5,
                5,
                6,
                12,
                5,
                13
            ],
            1.0883256188229034,
            1.0883256188229034
        ],
        [
            182,
            [
                2,
                0,
                3,
                9,
                0,
                6,
                7,
                7,
                8,
                7
            ],
            0.9236367579605145,
            0.9236367579605145
        ],
        [
            183,
            [
                6,
                0,
                13,
                5,
                12,
                11,
                3,
                1,
                3,
                5
            ],
            1.1117239777611985,
            1.1117239777611985
        ],
        [
            184,
            [
                4,
                5,
                6,
                12,
                13,
                5,
                6,
                7,
                12,
                4
            ],
            1.0760096222422029,
            1.0760096222422029
        ],
        [
            185,
            [
                2,
                9,
                10,
                11,
                12,
                9,
                0,
                8,
                6,
                12
            ],
            1.1110926128282763,
            1.1110926128282763
        ],
        [
            186,
            [
                2,
                6,
                3,
                9,
                13,
                12,
                0,
                8,
                7,
                11
            ],
            1.0875304015465859,
            1.0875304015465859
        ],
        [
            187,
            [
                6,
                13,
                4,
                12,
                5,
                13,
                0,
                4,
                5,
                11
            ],
            1.0554130538201552,
            1.0554130538201552
        ],
        [
            188,
            [
                6,
                7,
                4,
                12,
                5,
                13,
                7,
                6,
                5,
                12
            ],
            1.1126848758967565,
            1.1126848758967565
        ],
        [
            189,
            [
                0,
                4,
                1,
                2,
                11,
                8,
                12,
                6,
                3,
                11
            ],
            1.0827032461239516,
            1.0827032461239516
        ],
        [
            190,
            [
                6,
                7,
                4,
                5,
                5,
                5,
                13,
                4,
                13,
                11
            ],
            1.0352609344849326,
            1.0352609344849326
        ],
        [
            191,
            [
                2,
                3,
                9,
                10,
                12,
                2,
                7,
                3,
                13,
                5
            ],
            1.0734759081925829,
            1.0734759081925829
        ],
        [
            192,
            [
                0,
                1,
                6,
                13,
                4,
                13,
                1,
                5,
                1,
                4
            ],
            1.0987313618050416,
            1.0987313618050416
        ],
        [
            193,
            [
                6,
                0,
                2,
                13,
                9,
                3,
                8,
                12,
                7,
                11
            ],
            1.0941124705657808,
            1.0941124705657808
        ],
        [
            194,
            [
                0,
                6,
                2,
                13,
                4,
                3,
                8,
                7,
                13,
                11
            ],
            1.0790930874538331,
            1.0790930874538331
        ],
        [
            195,
            [
                6,
                0,
                7,
                7,
                13,
                5,
                7,
                7,
                6,
                12
            ],
            1.1150965704033948,
            1.1150965704033948
        ],
        [
            196,
            [
                6,
                0,
                2,
                9,
                3,
                7,
                13,
                8,
                6,
                7
            ],
            1.104330137682978,
            1.104330137682978
        ],
        [
            197,
            [
                6,
                13,
                12,
                5,
                13,
                6,
                5,
                5,
                7,
                11
            ],
            1.1156577170422617,
            1.1156577170422617
        ],
        [
            198,
            [
                6,
                0,
                13,
                5,
                6,
                7,
                4,
                5,
                7,
                11
            ],
            1.0896116810310417,
            1.0896116810310417
        ],
        [
            199,
            [
                6,
                0,
                13,
                1,
                5,
                6,
                12,
                7,
                13,
                12
            ],
            1.0966978797814304,
            1.0966978797814304
        ]
    ],
    "fine_tune_loss": [
        -0.6852949298046455,
        -0.7559464576860218,
        -0.8042178058798113,
        -0.8422505185260402,
        -0.8741898755042814,
        -0.9020645791077619,
        -0.9269423620569829,
        -0.9493465042560408,
        -0.9694934236499038,
        -0.9874534931034405,
        -1.0032607741806892,
        -1.0169854797965119,
        -1.0287755307824729,
        -1.0388661430650545,
        -1.04755529573762,
        -1.0551525039595742,
        -1.0619223244897213,
        -1.068047474071497,
        -1.073623595542705,
        -1.0786804917428119,
        -1.0832161587102556,
        -1.0872307173868292,
        -1.090751128626643,
        -1.0938408659287266,
        -1.0965923190250928,
        -1.099105173154931,
        -1.1014600124284015,
        -1.103698764310446,
        -1.105819846410639,
        -1.1077885129355243,
        -1.1095567433051994,
        -1.1110845467589534,
        -1.1123552722640422,
        -1.1133802404680968,
        -1.11419211073315,
        -1.1148309284418119,
        -1.115329793700714,
        -1.1157066735713221,
        -1.1159652191445995,
        -1.1161028650990843,
        -1.1161214442752232,
        -1.1160350591431212,
        -1.1158717102664932,
        -1.1156682670850184,
        -1.1154614859429262,
        -1.1152794719520076,
        -1.1151373677404686,
        -1.1150385828154872,
        -1.1149800621413466,
        -1.1149584077049497,
        -1.1149737387501604,
        -1.1150297274494523,
        -1.1151304046522008,
        -1.1152759895171547,
        -1.1154603092024034,
        -1.1156712564252875,
        -1.1158939352046175,
        -1.1161147353498242,
        -1.1163242687567372,
        -1.1165179319026766,
        -1.1166942698116218,
        -1.1168524818574974,
        -1.1169906870951727,
        -1.1171058744193212,
        -1.1171953118310736,
        -1.1172583168357881,
        -1.1172971813440278,
        -1.1173166768672285,
        -1.1173224821522587,
        -1.117319489896652,
        -1.1173109110321287,
        -1.117298495692151,
        -1.117283469815762,
        -1.1172674140916257,
        -1.1172524802000419,
        -1.1172408746473372,
        -1.1172340528074738,
        -1.1172322202236917,
        -1.1172344718173253,
        -1.1172394396052714,
        -1.117245999424593,
        -1.117253607595929,
        -1.1172621452017737,
        -1.117271496347314,
        -1.1172812308989302,
        -1.1172906259866235,
        -1.1172989758294403,
        -1.1173059291103218,
        -1.117311600157515,
        -1.1173163930070384,
        -1.1173206922806083,
        -1.1173246503780032,
        -1.117328197445065,
        -1.117331218123526,
        -1.117333724565174,
        -1.1173358865031644,
        -1.1173379131607797,
        -1.1173399013269132,
        -1.1173417773376746,
        -1.1173433707830034,
        -1.1173445488932512,
        -1.1173453020470767,
        -1.1173457246588443,
        -1.1173459266197243,
        -1.1173459599072901,
        -1.11734581809022,
        -1.1173454957604154,
        -1.1173450452903526,
        -1.117344578725112,
        -1.1173442163876341,
        -1.1173440293805874,
        -1.1173440225062086,
        -1.1173441637625885,
        -1.1173444266913992,
        -1.1173448070763805,
        -1.1173453051363507,
        -1.1173458973586814,
        -1.1173465284662332,
        -1.1173471315665406,
        -1.1173476575406955,
        -1.1173480884796787,
        -1.11734842748563,
        -1.1173486791402416,
        -1.117348840478899,
        -1.1173489085821933,
        -1.1173488935704876,
        -1.117348821843245,
        -1.11734872578474,
        -1.1173486298023136,
        -1.117348544924354,
        -1.1173484744632098,
        -1.117348422564651,
        -1.1173483964068291,
        -1.1173484010205879,
        -1.117348433642858,
        -1.1173484842172177,
        -1.1173485415631466,
        -1.1173485990223397,
        -1.117348654734668,
        -1.117348707758334,
        -1.1173487551253496,
        -1.117348792921454,
        -1.1173488195615302,
        -1.1173488372221594,
        -1.1173488498656985,
        -1.1173488601414168,
        -1.117348868336105,
        -1.1173488739160693,
        -1.1173488773954166,
        -1.1173488803574345,
        -1.1173488839146355,
        -1.117348887646911,
        -1.1173488902482804,
        -1.1173488910138532,
        -1.1173488904638995,
        -1.1173488896041153,
        -1.1173488889076992,
        -1.117348888212065,
        -1.1173488874487256,
        -1.117348887150852,
        -1.1173488881034441,
        -1.1173488906194857,
        -1.1173488943176633,
        -1.1173488985773368,
        -1.117348903041582,
        -1.1173489076042926,
        -1.117348912043659,
        -1.1173489158726222,
        -1.1173489186158805,
        -1.1173489201499924,
        -1.1173489206994203,
        -1.1173489205479825,
        -1.11734891984971,
        -1.1173489187224903,
        -1.1173489174139597,
        -1.1173489162700543,
        -1.117348915537555,
        -1.1173489152523495,
        -1.117348915330176,
        -1.1173489157107979,
        -1.1173489163728467,
        -1.1173489172434088,
        -1.1173489181650706,
        -1.1173489189804722,
        -1.117348919623576,
        -1.117348920107925,
        -1.1173489204498643,
        -1.117348920639162,
        -1.117348920681515,
        -1.117348920631968,
        -1.1173489205628213,
        -1.1173489205105525,
        -1.117348920471452,
        -1.1173489204403857,
        -1.1173489204310156,
        -1.1173489204545015,
        -1.1173489204977745,
        -1.1173489205369698,
        -1.1173489205648122,
        -1.11734892059268,
        -1.1173489206292604,
        -1.1173489206700256,
        -1.117348920709554,
        -1.117348920752904,
        -1.1173489208077203,
        -1.117348920870978,
        -1.1173489209309777,
        -1.1173489209799319,
        -1.1173489210178273,
        -1.1173489210447674,
        -1.117348921056714,
        -1.1173489210514698,
        -1.117348921034178,
        -1.1173489210133645,
        -1.1173489209941216,
        -1.117348920978158,
        -1.1173489209681533,
        -1.1173489209678145,
        -1.1173489209776901,
        -1.1173489209940977,
        -1.1173489210128775,
        -1.1173489210319716,
        -1.117348921049849,
        -1.1173489210638954,
        -1.117348921072059,
        -1.1173489210748262,
        -1.117348921074186,
        -1.1173489210714664,
        -1.117348921067322,
        -1.1173489210630079,
        -1.1173489210601208,
        -1.1173489210592054,
        -1.1173489210596548,
        -1.117348921060931,
        -1.1173489210629877,
        -1.1173489210655485,
        -1.1173489210679024,
        -1.1173489210696483,
        -1.117348921071022,
        -1.1173489210722791,
        -1.1173489210733192,
        -1.1173489210740712,
        -1.1173489210747451,
        -1.1173489210754723,
        -1.1173489210760645,
        -1.117348921076334,
        -1.1173489210763514,
        -1.1173489210762328,
        -1.1173489210759544,
        -1.1173489210755385,
        -1.1173489210751784,
        -1.1173489210750474,
        -1.1173489210751422,
        -1.117348921075415,
        -1.117348921075872,
        -1.1173489210764678,
        -1.1173489210770515,
        -1.1173489210774998,
        -1.1173489210777934,
        -1.1173489210779342,
        -1.1173489210779053,
        -1.1173489210777448,
        -1.1173489210775467,
        -1.1173489210773817,
        -1.1173489210772665,
        -1.1173489210772198,
        -1.1173489210772634,
        -1.1173489210773722,
        -1.1173489210774998,
        -1.1173489210776213,
        -1.1173489210777308,
        -1.1173489210778087,
        -1.1173489210778453,
        -1.1173489210778569,
        -1.1173489210778589,
        -1.117348921077854,
        -1.1173489210778456,
        -1.1173489210778424,
        -1.117348921077846,
        -1.1173489210778476,
        -1.1173489210778464,
        -1.1173489210778467,
        -1.1173489210778496,
        -1.1173489210778513,
        -1.1173489210778589,
        -1.117348921077873,
        -1.1173489210778909,
        -1.1173489210779077,
        -1.1173489210779257,
        -1.117348921077939,
        -1.117348921077944,
        -1.1173489210779417,
        -1.117348921077936,
        -1.1173489210779284,
        -1.1173489210779193,
        -1.1173489210779148,
        -1.1173489210779153,
        -1.1173489210779193,
        -1.117348921077925,
        -1.117348921077933,
        -1.11734892107794,
        -1.1173489210779441,
        -1.117348921077946,
        -1.1173489210779464,
        -1.1173489210779446,
        -1.117348921077943,
        -1.1173489210779426,
        -1.1173489210779413,
        -1.1173489210779397,
        -1.1173489210779421,
        -1.1173489210779426,
        -1.117348921077943,
        -1.1173489210779441,
        -1.117348921077945,
        -1.1173489210779453,
        -1.1173489210779457,
        -1.1173489210779461,
        -1.1173489210779466,
        -1.1173489210779468,
        -1.1173489210779475,
        -1.1173489210779466,
        -1.1173489210779473,
        -1.1173489210779464,
        -1.117348921077946,
        -1.1173489210779468,
        -1.1173489210779461,
        -1.1173489210779466,
        -1.117348921077947,
        -1.1173489210779473,
        -1.117348921077948,
        -1.1173489210779477,
        -1.1173489210779477,
        -1.117348921077947,
        -1.1173489210779473,
        -1.1173489210779475,
        -1.1173489210779468,
        -1.1173489210779473,
        -1.117348921077947,
        -1.1173489210779475,
        -1.1173489210779484,
        -1.1173489210779475,
        -1.1173489210779477,
        -1.117348921077948,
        -1.1173489210779473,
        -1.117348921077948,
        -1.1173489210779481,
        -1.1173489210779481,
        -1.1173489210779481,
        -1.1173489210779486,
        -1.1173489210779481,
        -1.1173489210779477,
        -1.117348921077948,
        -1.1173489210779484,
        -1.117348921077948,
        -1.117348921077948,
        -1.1173489210779477,
        -1.1173489210779481,
        -1.1173489210779488,
        -1.1173489210779484,
        -1.1173489210779486,
        -1.1173489210779484,
        -1.1173489210779477,
        -1.1173489210779475,
        -1.1173489210779473,
        -1.1173489210779477,
        -1.1173489210779484,
        -1.1173489210779481,
        -1.117348921077948,
        -1.1173489210779477,
        -1.1173489210779477,
        -1.1173489210779484,
        -1.1173489210779477,
        -1.1173489210779481,
        -1.117348921077948,
        -1.1173489210779475,
        -1.117348921077948,
        -1.1173489210779475,
        -1.1173489210779475,
        -1.1173489210779481,
        -1.1173489210779475,
        -1.1173489210779486,
        -1.117348921077948,
        -1.117348921077948,
        -1.117348921077948,
        -1.117348921077948,
        -1.1173489210779481,
        -1.1173489210779477,
        -1.1173489210779477,
        -1.1173489210779475,
        -1.1173489210779473,
        -1.1173489210779484,
        -1.1173489210779477,
        -1.1173489210779477,
        -1.1173489210779477,
        -1.1173489210779481,
        -1.1173489210779477,
        -1.117348921077948,
        -1.117348921077948,
        -1.1173489210779481,
        -1.1173489210779477
    ]
}